hashedixsearch/__init__.py
hashedixsearch/_utils.py
hashedixsearch/search.py
hashedixsearch-1.2.3.dist-info/LICENSE
hashedixsearch-1.2.3.dist-info/METADATA
hashedixsearch-1.2.3.dist-info/WHEEL
hashedixsearch-1.2.3.dist-info/top_level.txt
hashedixsearch-1.2.3.dist-info/RECORD
