Metadata-Version: 2.1
Name: hashedixsearch
Version: 1.2.3
Summary: in-process search-engine for python
Author-email: James Addison <james@reciperadar.com>
License: AGPL-3.0-or-later
Project-URL: Homepage, https://pypi.org/project/hashedixsearch/
Project-URL: Source, https://github.com/openculinary/hashedixsearch.git/
Classifier: License :: OSI Approved :: GNU Affero General Public License v3 or later (AGPLv3+)
Requires-Python: >=3.8
License-File: LICENSE
Requires-Dist: hashedindex (>=0.10.0)
